__init__.py
mcpcan.py
utils.py
python_can_mcpcan-0.1.6.dist-info/METADATA
python_can_mcpcan-0.1.6.dist-info/WHEEL
python_can_mcpcan-0.1.6.dist-info/entry_points.txt
python_can_mcpcan-0.1.6.dist-info/top_level.txt
python_can_mcpcan-0.1.6.dist-info/RECORD
