Metadata-Version: 2.1
Name: python-can-mcpcan
Version: 0.1.6
Summary: Python-can MCPcan
Home-page: https://github.com/xxx
Author: SoftMagic
Author-email: softmajik@gmail.com
Requires-Python: >=3.11
Requires-Dist: python-can
